{
  "name": "nicotiana rustica",
  "commonname": "midewiwan sacred tobacco",
  "description": "There are a number of common names in use for this species including: Wild Tobacco, Shamanic Tobacco, Erowid Tobacco or Aztec Tobacco. In South America it is traditionally called Mapacho.  Midewiwan Sacred Tobacco is an annual; it completes its life cycle during one season but will re-seed.",
  "prices": [
    {
      "quantity": 1,
      "unit": "packet",
      "price": 2.5
    },
    {
      "quantity": 0.125,
      "unit": "oz",
      "price": 7.5
    },
    {
      "quantity": 0.25,
      "unit": "oz",
      "price": 12
    },
    {
      "quantity": 0.5,
      "unit": "oz",
      "price": 19.5
    },
    {
      "quantity": 1,
      "unit": "oz",
      "price": 30
    }
  ],
  "seeds/packet": 250,
  "seeds/ounce": 130000,
  "germination": [
    "A",
    "D"
  ],
  "light": [
    "Full",
    "Partial"
  ],
  "moisture": [
    "Medium",
    "Medium-Dry"
  ],
  "height": 24,
  "blooms": [
    "July",
    "August",
    "September"
  ],
  "color": [
    "Yellow"
  ],
  "features": [
    "Deer Resistant (Our experiences here in the Upper Midwest may vary in other regions; deer can respond differently to local conditions or seasonal variations.)"
  ],
  "sku": "NIC02F"
}